pycleaner/__init__.py
pycleaner/cli.py
pycleaner/core.py
pycleaner/data.py
pycleaner/utils.py
import_stripper-0.1.0.dist-info/METADATA
import_stripper-0.1.0.dist-info/WHEEL
import_stripper-0.1.0.dist-info/entry_points.txt
import_stripper-0.1.0.dist-info/top_level.txt
import_stripper-0.1.0.dist-info/RECORD
